control.v
/* 
Module => control
Purpose => main controller of the design
        Generates various control signals needed in the design
*/


module control(  input clk, input rst, input [6:0] instOpcode, 
                output reg IorDSelector, output reg ce, output reg oce, output reg wre, output reg pcWriteEnable, output reg pcWriteCond, output reg pcSource, output reg memtoRegSelect, output reg irWriteEnable, 
                        output reg regWriteEnable, output reg aluSrcASelect, output reg [1:0] aluSrcBSelect, output reg [1:0] aluOp );
    
    // 10 States - one hot encoding
    reg [10:0] currentState;
    reg [10:0] nextState;
    // state definition
    localparam
        idle =                  11'b00000000001,
        instFetch =             11'b00000000010,
        instDecodeRegFetch =    11'b00000000100,
        memoryAddrCompute =     11'b00000001000,
        memoryReadAccess =      11'b00000010000,
        memoryReadComplete =    11'b00000100000,
        mdrToRegFile =          11'b00001000000,
        memoryWriteAccess =     11'b00010000000,
        rTypeExecute =          11'b00100000000,
        rTypeComplete =         11'b01000000000,
        branchComplete =        11'b10000000000;
    
    // Sequential logic for state transition
    // asynchronous rst
    always@(posedge clk or posedge rst) begin
        if(rst) begin
            // reset to initial state
            currentState <= idle;
        end else begin
            // state transition
            currentState <= nextState;
        end
    end

    always@(*) begin
        //Default assignments
        nextState = currentState;
        IorDSelector = 1'b0;
        // memory controls
        ce = 1'b0;  // clock enable input for memory, active high
        oce = 1'b0; // output clock enable for memory, signal used in pipeline, invalid in Bypass
        wre = 1'b0; // write enable input, 1: write, 0: read
        pcWriteEnable = 1'b0;
        pcWriteCond = 1'b0;
        pcSource = 1'b0;
        memtoRegSelect = 1'b0;
        irWriteEnable = 1'b0;
        regWriteEnable = 1'b0;
        aluSrcASelect = 1'b0;
        aluSrcBSelect = 2'b00;
        aluOp = 2'b00;

        // state machine logic
        case(currentState)
            // idle state hex is 1
            idle: begin
                nextState = instFetch;
            end
            // instFetch state hex is 2
            instFetch: begin
                nextState = instDecodeRegFetch;
                // enables and selectors
                IorDSelector = 1'b0;
                ce = 1'b1;
                oce = 1'b1;
                wre = 1'b0;
                pcWriteEnable = 1'b1;
                pcWriteCond = 1'b0;
                pcSource = 1'b0;
                memtoRegSelect = 1'b0;
                irWriteEnable = 1'b1;
                regWriteEnable = 1'b0;
                aluSrcASelect = 1'b0;
                aluSrcBSelect = 2'b01;
                aluOp = 2'b00;
            end
            // instDecodeRegFetch state hex is 4
            instDecodeRegFetch: begin
                if(instOpcode == 7'h03) begin
                    nextState = memoryAddrCompute;
                end 
                else if (instOpcode == 7'h63) begin
                    nextState = branchComplete;
                end 
                else begin
                    nextState = rTypeExecute;
                end
                ce = 1'b0;
                oce = 1'b0;
                // changing ALU input to immediate generator output to calculate branch address
                aluSrcASelect = 1'b0;
                aluSrcBSelect = 2'b10;
                aluOp = 2'b00;
            end
            // memoryAddrCompute state hex is 8
            memoryAddrCompute: begin
                if(instOpcode == 7'h03) begin
                    nextState = memoryReadAccess;
                end else begin
                    nextState = memoryWriteAccess;
                end
                aluSrcASelect = 1'b1;
                aluSrcBSelect = 2'b10;
                aluOp = 2'b00;
            end
            // memoryReadAccess state hex is 10
            memoryReadAccess: begin
                nextState = memoryReadComplete;
                ce = 1'b1;
                oce = 1'b1;
                IorDSelector = 1'b1;
                aluSrcASelect = 1'b1;
                aluSrcBSelect = 2'b10;
                aluOp = 2'b00;
            end
            // memoryReadComplete state hex is 20
            memoryReadComplete: begin
                nextState = mdrToRegFile;
                ce = 1'b0;
                oce = 1'b0;
                IorDSelector = 1'b0;
                memtoRegSelect = 1'b1;
                regWriteEnable = 1'b1;
            end
            // mdrToRegFile state hex is 40
            mdrToRegFile: begin
                nextState = instFetch;
                ce = 1'b0;
                oce = 1'b0;
                IorDSelector = 1'b0;
                memtoRegSelect = 1'b1;
                regWriteEnable = 1'b1;
            end
            // memoryWriteAccess state hex is 80
            memoryWriteAccess: begin
                nextState = instFetch;
                ce = 1'b1;
                oce = 1'b1;
                wre = 1'b1;
                IorDSelector = 1'b1;
            end
            // rTypeExecute state hex is 100
            rTypeExecute: begin
                nextState = rTypeComplete;
                aluSrcASelect = 1'b1;
                aluSrcBSelect = 2'b00;
                // aluOp = 2'10 indicates that the operation will be decided by opcode of instruction
                aluOp = 2'b10;
            end
            // rTypeComplete state hex is 200
            rTypeComplete: begin
                nextState = instFetch;
                regWriteEnable = 1'b1;
                memtoRegSelect = 1'b0;
            end
            // branchComplete state hex is 400
            branchComplete: begin
                nextState = instFetch;
                aluSrcASelect = 1'b1;
                aluSrcBSelect = 2'b00;
                // aluOp = 2'b01 indicated that the operation will be subtraction
                aluOp = 2'b01;
                pcWriteCond = 1'b1;
                pcSource = 1'b1;
            end
            default: begin
                nextState = idle;
                IorDSelector = 1'b0;
                ce = 1'b0;  
                oce = 1'b0; 
                wre = 1'b0; 
                pcWriteEnable = 1'b0;
                pcWriteCond = 1'b0;
                pcSource = 1'b0;
                memtoRegSelect = 1'b0;
                irWriteEnable = 1'b0;
                regWriteEnable = 1'b0;
                aluSrcASelect = 1'b0;
                aluSrcBSelect = 2'b00;
                aluOp = 2'b00;
            end
        endcase
    end



endmodule

top.v
/* 
Module => top
Purpose => top module of the design 
Input description =>
    1. clk => central ticker of the system, on each positive edge of the clock things happen
    2. rst => reset signal of the system
Output description =>
    1. fDataOut => 6 bit output data to visualize on 6 LEDs of tang nano 9k
*/

`include "alu.v"
`include "rf.v"
`include "immGen.v"
`include "control.v"
`include "basicMemory.v"
//`include "gowin_sp/gowin_sp.v"

module mux2 (input [31:0] in0, in1, input select, output reg [31:0] out);
    always @(*) begin
        case(select)
            1'b0: out = in0;
            1'b1: out = in1;
        endcase
    end
endmodule

module mux3 (input [31:0] in0, in1, in2, input [1:0] select, output reg [31:0] out);
    always @(*) begin
        case(select)
            2'b00: out = in0;
            2'b01: out = in1;
            2'b10: out = in2;
            default: out = in1;
        endcase
    end
endmodule

module regWithEnable (input clk, input rst ,input enable, input [31:0] regIn, output reg [31:0] regOut);
    always@(posedge clk) begin
        if(rst == 1'b1) begin
            regOut <= 32'h0000;
        end
        else begin
            if(enable == 1'b1) begin
                regOut <= regIn;
            end
        end
    end
endmodule

module regWithoutEnable (input clk, input rst, input [31:0] regIn, output reg [31:0] regOut);
    always@(posedge clk) begin
        if(rst == 1'b1) begin
            regOut <= 32'h0000;
        end
        else begin
            regOut <= regIn;
        end
    end
endmodule

module top( input clk, nrst, output [5:0] fDataOut);

    // on tang nano, buttons are pulled high so whenever the button is pressed, we get low so our rst will be active low. hence the name nrst.
    // converting acrive low reset of tang nano to active high
    wire rst = !nrst;

    wire [31:0] addrOutPcNet, pcSourceMuxOutNet;
    wire [31:0] aluOutNet, aluRegOutNet;
    wire [31:0] memoryDataOutNet;
    wire [31:0] irOutNet;
    wire [31:0] mdrOutNet;
    wire [31:0] rfWriteDataMuxOutNet;
    wire [31:0] readData1Net;
    wire [31:0] readData2Net;
    wire [31:0] arOutNet;
    wire [31:0] brOutNet;
    wire [31:0] aluAmuxOutNet;
    wire [31:0] aluBmuxOutNet;
    wire [31:0] immGenOutNet;
    wire [31:0] IorDmuxOutNet;
    wire IorDSelectorNet, ceNet, oceNet, wreNet, pcWriteEnableNet, pcWriteCondNet, pcSourceNet, memtoRegSelectNet, irWriteEnableNet, regWriteEnableNet, aluSrcASelectNet;
    wire [1:0] aluSrcBSelectNet;
    wire [1:0] aluOpNet;
    wire aluIsZeroNet;
    reg isZeroAndPcWriteCond, finalPcEnableNet;

    always @(*) begin
        isZeroAndPcWriteCond <= pcWriteCondNet && aluIsZeroNet ;
        finalPcEnableNet <= isZeroAndPcWriteCond || pcWriteEnableNet ;
    end

   
    // instantiating all the modules
    regWithEnable u_pc(.clk(clk), .rst(rst), .enable(finalPcEnableNet), .regIn(pcSourceMuxOutNet), .regOut(addrOutPcNet));
    mux2 u_pcSourceMux(.in0(aluOutNet), .in1(aluRegOutNet), .select(pcSourceNet), .out(pcSourceMuxOutNet));
    mux2 u_IorDmux(.in0(addrOutPcNet), .in1(aluRegOutNet), .select(IorDSelectorNet), .out(IorDmuxOutNet));
    //Gowin_SP u_spmem(.dout(memoryDataOutNet), .clk(clk), .oce(oceNet), .ce(ceNet), .reset(rst), .wre(wreNet), .ad(IorDmuxOutNet[7:0]), .din(brOutNet));
    basicMemory u_basicMemory(.clk(clk), .rst(rst), .ce(ceNet), .wre(wreNet), .ad(IorDmuxOutNet[7:0]), .din(brOutNet), .dout(memoryDataOutNet));
    regWithEnable u_ir(.clk(clk), .rst(rst), .enable(irWriteEnableNet), .regIn(memoryDataOutNet), .regOut(irOutNet));
    regWithoutEnable u_mdr(.clk(clk), .rst(rst), .regIn(memoryDataOutNet), .regOut(mdrOutNet));
    mux2 u_rfWriteDataMux(.in0(aluRegOutNet), .in1(mdrOutNet), .select(memtoRegSelectNet), .out(rfWriteDataMuxOutNet));
    rf u_rf(.clk(clk), .regWriteEnable(regWriteEnableNet), .readReg1(irOutNet[19:15]), .readReg2(irOutNet[24:20]), .writeReg(irOutNet[11:7]), .readData1(readData1Net), .readData2(readData2Net),.writeData(rfWriteDataMuxOutNet));
    regWithoutEnable u_ar(.clk(clk), .rst(rst), .regIn(readData1Net), .regOut(arOutNet));
    mux2 u_aluAmux(.in0(addrOutPcNet), .in1(arOutNet), .select(aluSrcASelectNet), .out(aluAmuxOutNet));
    regWithoutEnable u_br(.clk(clk), .rst(rst), .regIn(readData2Net), .regOut(brOutNet));
    mux3 u_aluBmux(.in0(brOutNet),.in1(32'h00000004),.in2(immGenOutNet),.select(aluSrcBSelectNet),.out(aluBmuxOutNet));
    immGen u_immGen(.instr(irOutNet),.imm(immGenOutNet));
    alu u_alu(.ALUop(aluOpNet), .instOpcode(irOutNet[6:0]), .A(aluAmuxOutNet), .B(aluBmuxOutNet), .Z(aluOutNet), .isZero(aluIsZeroNet));
    regWithoutEnable u_alur(.clk(clk),  .rst(rst), .regIn(aluOutNet), .regOut(aluRegOutNet));
    control u_control(.clk(clk), .rst(rst), .instOpcode(irOutNet[6:0]), .IorDSelector(IorDSelectorNet), .ce(ceNet), .oce(oceNet), .wre(wreNet), .pcWriteEnable(pcWriteEnableNet),
                .pcWriteCond(pcWriteCondNet), .pcSource(pcSourceNet), .memtoRegSelect(memtoRegSelectNet), .irWriteEnable(irWriteEnableNet), .regWriteEnable(regWriteEnableNet),
                .aluSrcASelect(aluSrcASelectNet), .aluSrcBSelect(aluSrcBSelectNet), .aluOp(aluOpNet));

    assign fDataOut = aluRegOutNet[5:0];
endmodule

/*
Commands to generate waveform-
iverilog -o top_tb.vvp top_tb.v
vvp top_tb.vvp
gtkwave top_tb.vcd signals.gtkw
*/

alu.v
/* 
Module => alu
Purpose => Arithmetic Logic Unit i.e. the computation unit of the CPU
Input description =>
    1. ALUop - 2 bit operational code sent to ALU from control unit
    2. instOpcode - instruction opcode to decide ALU function 
    3. A - 32 bit operand
    4. B - 32 bit operand
Output description =>
    1. Z - ALU output
    2. isZero - 1 bit flag which indicates if z is equal to 0
*/
module alu(input [1:0] ALUop, input [6:0] instOpcode, input [31:0] A , input [31:0] B, output reg [31:0] Z, output reg isZero);

always@(*) begin
    case(ALUop)
        2'b00: begin 
            Z = A + B ;
        end
        2'b01: begin
            Z = A - B ;
        end
        // following two are fake, need to update
        2'b10: begin
            if (instOpcode == 7'h33) begin
                // 7'h33 is opcode for add
                // TODO -- need to add funct3 and funct7 bits also as sub has same opcode but different funct bits
                Z = A + B; 
            end else begin
                Z = A - B;
            end
        end
        2'b11: Z = A + B ;
    endcase
end

always @(*) begin
    if (Z == 32'b0) begin
        isZero <= 1'b1;
    end else begin
        isZero <= 1'b0;
    end
end

endmodule

immGen.v
/* 
Module => immGen
Purpose => Immediate generation unit, it has to generate 32bit immediates from all types of instructions. 
Input description =>
    1. instr - 32 bit instruction
Output description =>
    1. imm - 32 bit immediate
*/
module immGen( input [31:0] instr, output reg [31:0] imm);
always@(*) begin
    if (instr[6:0] == 7'h03 && instr[14:12] == 3'b010) begin
        // immediate generation for 'lw'
        imm = {20'h00000,instr[31:20]};
    end else if (instr[6:0] == 7'h63 && instr[14:12] == 3'b000) begin
        // immediate generation for 'beq'
        if (instr[31] == 1'b1) begin
            imm = {20'hFFFFF,instr[31],instr[7],instr[30:25],instr[11:8],1'b0};
        end else begin
            imm = {20'h00000,instr[31],instr[7],instr[30:25],instr[11:8],1'b0};
        end
    end 
    else begin
        imm = 32'h0;
    end
end
endmodule

rf.v
/* 
Module => rf
Purpose => register file, it containts all the 32 registers of RISC-V CPU
Input description =>
    1. clk => central ticker of the system, on each positive edge of the clock, it loads the input value
    2. regWriteEnable => active high signal to enable writing to the register file
    3. readReg1 and readReg2 => 5 bit address of the registers whose data needs to be presented on readData1 and readData2 respectively
    4. writeReg => 5 bit address of regiser to be written
    5. writeData => data to write in register selected by writeReg
Output description =>
    1. readData1 and readData2 => output data from registers specified by readReg1 and readReg2 respectively
*/
module rf(input clk, input regWriteEnable,
                     input [4:0] readReg1,
                     input [4:0] readReg2, 
                     input [4:0] writeReg, input [31:0] writeData, 
                    output reg [31:0] readData1, output reg [31:0] readData2);

    // 32 registers each 32 bit wide
    reg [31:0] registersOfRegFile [31:0];
    // setting 0 register to always be 0
    initial begin
        registersOfRegFile[0] <= 32'b0; 
    end


    // write logic
    genvar i;
    generate 
        for (i=0; i<32; i=i+1) begin: reg_write
            always@(posedge clk) begin
                if (regWriteEnable == 1'b1 && (writeReg == i) && (writeReg != 5'b0)) begin
                    registersOfRegFile[i] <= writeData ;
                end 
            end
        end
    endgenerate


    //read logic
    always @(posedge clk) begin
        readData1 = registersOfRegFile[readReg1];
        readData2 = registersOfRegFile[readReg2];
    end
endmodule

basicMemory.v
/* creating basic memory to help simulation in vscode, as gowin IP won't work. */

module basicMemory(input clk, input rst, input ce, input wre, input [7:0] ad, input [31:0] din, output reg [31:0] dout);

    reg [31:0] memStoreArray [255:0];

    initial begin
        memStoreArray[0] = 32'h02802483;  // lw x9, 40(x0)
        memStoreArray[4] = 32'h02C02503;  // lw x10, 44(x0)
        memStoreArray[8] = 32'h00A485B3;  // add x11, x9, x10
        memStoreArray[12] = 32'hFE000EE3; // beq x0, x0, -4 ; instruction format is B type so needs special treatment for immediate generation
        memStoreArray[40] = 32'h00000006;
        memStoreArray[44] = 32'h00000005;
    end

    always@(posedge clk) begin
        if(wre) begin
            memStoreArray[ad] <= din;
        end else begin
           dout <= memStoreArray[ad]; 
        end
    end

endmodule

top_tb.v
`timescale 1ns / 1ns
`include "top.v"

module top_tb;

reg clk = 0;
reg nrst;
wire [5:0] fDataOut;

top u_top(.clk(clk), .nrst(nrst),.fDataOut(fDataOut));

always begin
    clk = ~clk;
    #10;
end

initial begin
    $dumpfile("top_tb.vcd");
    $dumpvars(0, top_tb);

    #10
    nrst = 1'b0;
    #40
    nrst = 1'b1;

    #1000

    #10
    nrst = 1'b0;
    #40
    nrst = 1'b1;

    #1000

    $finish;
end

endmodule

top_tb.vcd
$date
	Sat Dec 28 22:09:08 2024
$end
$version
	Icarus Verilog
$end
$timescale
	1ns
$end
$scope module top_tb $end
$var wire 6 ! fDataOut [5:0] $end
$var reg 1 " clk $end
$var reg 1 # nrst $end
$scope module u_top $end
$var wire 1 " clk $end
$var wire 1 # nrst $end
$var wire 1 $ wreNet $end
$var wire 1 % rst $end
$var wire 32 & rfWriteDataMuxOutNet [31:0] $end
$var wire 1 ' regWriteEnableNet $end
$var wire 32 ( readData2Net [31:0] $end
$var wire 32 ) readData1Net [31:0] $end
$var wire 1 * pcWriteEnableNet $end
$var wire 1 + pcWriteCondNet $end
$var wire 1 , pcSourceNet $end
$var wire 32 - pcSourceMuxOutNet [31:0] $end
$var wire 1 . oceNet $end
$var wire 1 / memtoRegSelectNet $end
$var wire 32 0 memoryDataOutNet [31:0] $end
$var wire 32 1 mdrOutNet [31:0] $end
$var wire 1 2 irWriteEnableNet $end
$var wire 32 3 irOutNet [31:0] $end
$var wire 32 4 immGenOutNet [31:0] $end
$var wire 6 5 fDataOut [5:0] $end
$var wire 1 6 ceNet $end
$var wire 32 7 brOutNet [31:0] $end
$var wire 32 8 arOutNet [31:0] $end
$var wire 2 9 aluSrcBSelectNet [1:0] $end
$var wire 1 : aluSrcASelectNet $end
$var wire 32 ; aluRegOutNet [31:0] $end
$var wire 32 < aluOutNet [31:0] $end
$var wire 2 = aluOpNet [1:0] $end
$var wire 1 > aluIsZeroNet $end
$var wire 32 ? aluBmuxOutNet [31:0] $end
$var wire 32 @ aluAmuxOutNet [31:0] $end
$var wire 32 A addrOutPcNet [31:0] $end
$var wire 32 B IorDmuxOutNet [31:0] $end
$var wire 1 C IorDSelectorNet $end
$var reg 1 D finalPcEnableNet $end
$var reg 1 E isZeroAndPcWriteCond $end
$scope module u_IorDmux $end
$var wire 1 C select $end
$var wire 32 F in1 [31:0] $end
$var wire 32 G in0 [31:0] $end
$var reg 32 H out [31:0] $end
$upscope $end
$scope module u_alu $end
$var wire 7 I instOpcode [6:0] $end
$var wire 32 J B [31:0] $end
$var wire 2 K ALUop [1:0] $end
$var wire 32 L A [31:0] $end
$var reg 32 M Z [31:0] $end
$var reg 1 > isZero $end
$upscope $end
$scope module u_aluAmux $end
$var wire 1 : select $end
$var wire 32 N in1 [31:0] $end
$var wire 32 O in0 [31:0] $end
$var reg 32 P out [31:0] $end
$upscope $end
$scope module u_aluBmux $end
$var wire 32 Q in1 [31:0] $end
$var wire 2 R select [1:0] $end
$var wire 32 S in2 [31:0] $end
$var wire 32 T in0 [31:0] $end
$var reg 32 U out [31:0] $end
$upscope $end
$scope module u_alur $end
$var wire 1 " clk $end
$var wire 32 V regIn [31:0] $end
$var wire 1 % rst $end
$var reg 32 W regOut [31:0] $end
$upscope $end
$scope module u_ar $end
$var wire 1 " clk $end
$var wire 1 % rst $end
$var wire 32 X regIn [31:0] $end
$var reg 32 Y regOut [31:0] $end
$upscope $end
$scope module u_basicMemory $end
$var wire 8 Z ad [7:0] $end
$var wire 1 " clk $end
$var wire 1 % rst $end
$var wire 1 $ wre $end
$var wire 32 [ din [31:0] $end
$var wire 1 6 ce $end
$var reg 32 \ dout [31:0] $end
$upscope $end
$scope module u_br $end
$var wire 1 " clk $end
$var wire 1 % rst $end
$var wire 32 ] regIn [31:0] $end
$var reg 32 ^ regOut [31:0] $end
$upscope $end
$scope module u_control $end
$var wire 1 " clk $end
$var wire 7 _ instOpcode [6:0] $end
$var wire 1 % rst $end
$var parameter 11 ` branchComplete $end
$var parameter 11 a idle $end
$var parameter 11 b instDecodeRegFetch $end
$var parameter 11 c instFetch $end
$var parameter 11 d mdrToRegFile $end
$var parameter 11 e memoryAddrCompute $end
$var parameter 11 f memoryReadAccess $end
$var parameter 11 g memoryReadComplete $end
$var parameter 11 h memoryWriteAccess $end
$var parameter 11 i rTypeComplete $end
$var parameter 11 j rTypeExecute $end
$var reg 1 C IorDSelector $end
$var reg 2 k aluOp [1:0] $end
$var reg 1 : aluSrcASelect $end
$var reg 2 l aluSrcBSelect [1:0] $end
$var reg 1 6 ce $end
$var reg 11 m currentState [10:0] $end
$var reg 1 2 irWriteEnable $end
$var reg 1 / memtoRegSelect $end
$var reg 11 n nextState [10:0] $end
$var reg 1 . oce $end
$var reg 1 , pcSource $end
$var reg 1 + pcWriteCond $end
$var reg 1 * pcWriteEnable $end
$var reg 1 ' regWriteEnable $end
$var reg 1 $ wre $end
$upscope $end
$scope module u_immGen $end
$var wire 32 o instr [31:0] $end
$var reg 32 p imm [31:0] $end
$upscope $end
$scope module u_ir $end
$var wire 1 " clk $end
$var wire 1 2 enable $end
$var wire 32 q regIn [31:0] $end
$var wire 1 % rst $end
$var reg 32 r regOut [31:0] $end
$upscope $end
$scope module u_mdr $end
$var wire 1 " clk $end
$var wire 32 s regIn [31:0] $end
$var wire 1 % rst $end
$var reg 32 t regOut [31:0] $end
$upscope $end
$scope module u_pc $end
$var wire 1 " clk $end
$var wire 1 D enable $end
$var wire 1 % rst $end
$var wire 32 u regIn [31:0] $end
$var reg 32 v regOut [31:0] $end
$upscope $end
$scope module u_pcSourceMux $end
$var wire 32 w in0 [31:0] $end
$var wire 32 x in1 [31:0] $end
$var wire 1 , select $end
$var reg 32 y out [31:0] $end
$upscope $end
$scope module u_rf $end
$var wire 1 " clk $end
$var wire 5 z readReg1 [4:0] $end
$var wire 5 { readReg2 [4:0] $end
$var wire 1 ' regWriteEnable $end
$var wire 5 | writeReg [4:0] $end
$var wire 32 } writeData [31:0] $end
$var reg 32 ~ readData1 [31:0] $end
$var reg 32 !" readData2 [31:0] $end
$scope begin reg_write[0] $end
$var parameter 2 "" i $end
$upscope $end
$scope begin reg_write[1] $end
$var parameter 2 #" i $end
$upscope $end
$scope begin reg_write[2] $end
$var parameter 3 $" i $end
$upscope $end
$scope begin reg_write[3] $end
$var parameter 3 %" i $end
$upscope $end
$scope begin reg_write[4] $end
$var parameter 4 &" i $end
$upscope $end
$scope begin reg_write[5] $end
$var parameter 4 '" i $end
$upscope $end
$scope begin reg_write[6] $end
$var parameter 4 (" i $end
$upscope $end
$scope begin reg_write[7] $end
$var parameter 4 )" i $end
$upscope $end
$scope begin reg_write[8] $end
$var parameter 5 *" i $end
$upscope $end
$scope begin reg_write[9] $end
$var parameter 5 +" i $end
$upscope $end
$scope begin reg_write[10] $end
$var parameter 5 ," i $end
$upscope $end
$scope begin reg_write[11] $end
$var parameter 5 -" i $end
$upscope $end
$scope begin reg_write[12] $end
$var parameter 5 ." i $end
$upscope $end
$scope begin reg_write[13] $end
$var parameter 5 /" i $end
$upscope $end
$scope begin reg_write[14] $end
$var parameter 5 0" i $end
$upscope $end
$scope begin reg_write[15] $end
$var parameter 5 1" i $end
$upscope $end
$scope begin reg_write[16] $end
$var parameter 6 2" i $end
$upscope $end
$scope begin reg_write[17] $end
$var parameter 6 3" i $end
$upscope $end
$scope begin reg_write[18] $end
$var parameter 6 4" i $end
$upscope $end
$scope begin reg_write[19] $end
$var parameter 6 5" i $end
$upscope $end
$scope begin reg_write[20] $end
$var parameter 6 6" i $end
$upscope $end
$scope begin reg_write[21] $end
$var parameter 6 7" i $end
$upscope $end
$scope begin reg_write[22] $end
$var parameter 6 8" i $end
$upscope $end
$scope begin reg_write[23] $end
$var parameter 6 9" i $end
$upscope $end
$scope begin reg_write[24] $end
$var parameter 6 :" i $end
$upscope $end
$scope begin reg_write[25] $end
$var parameter 6 ;" i $end
$upscope $end
$scope begin reg_write[26] $end
$var parameter 6 <" i $end
$upscope $end
$scope begin reg_write[27] $end
$var parameter 6 =" i $end
$upscope $end
$scope begin reg_write[28] $end
$var parameter 6 >" i $end
$upscope $end
$scope begin reg_write[29] $end
$var parameter 6 ?" i $end
$upscope $end
$scope begin reg_write[30] $end
$var parameter 6 @" i $end
$upscope $end
$scope begin reg_write[31] $end
$var parameter 6 A" i $end
$upscope $end
$upscope $end
$scope module u_rfWriteDataMux $end
$var wire 32 B" in0 [31:0] $end
$var wire 32 C" in1 [31:0] $end
$var wire 1 / select $end
$var reg 32 D" out [31:0] $end
$upscope $end
$upscope $end
$upscope $end
$enddefinitions $end
$comment Show the parameter values. $end
$dumpall
b11111 A"
b11110 @"
b11101 ?"
b11100 >"
b11011 ="
b11010 <"
b11001 ;"
b11000 :"
b10111 9"
b10110 8"
b10101 7"
b10100 6"
b10011 5"
b10010 4"
b10001 3"
b10000 2"
b1111 1"
b1110 0"
b1101 /"
b1100 ."
b1011 -"
b1010 ,"
b1001 +"
b1000 *"
b111 )"
b110 ("
b101 '"
b100 &"
b11 %"
b10 $"
b1 #"
b0 ""
b100000000 j
b1000000000 i
b10000000 h
b100000 g
b10000 f
b1000 e
b1000000 d
b10 c
b100 b
b1 a
b10000000000 `
$end
#0
$dumpvars
bx D"
bx C"
bx B"
bx !"
bx ~
bx }
bx |
bx {
bx z
bx y
bx x
bx w
bx v
bx u
bx t
bx s
bx r
bx q
bx p
bx o
bx n
bx m
bx l
bx k
bx _
bx ^
bx ]
bx \
bx [
bx Z
bx Y
bx X
bx W
bx V
b100 U
bx T
bx S
bx R
b100 Q
bx P
bx O
bx N
bx M
bx L
bx K
b100 J
bx I
bx H
bx G
bx F
xE
xD
xC
bx B
bx A
bx @
b100 ?
x>
bx =
bx <
bx ;
x:
bx 9
bx 8
bx 7
x6
bx 5
bx 4
bx 3
x2
bx 1
bx 0
x/
x.
bx -
x,
x+
x*
bx )
bx (
x'
bx &
x%
x$
x#
1"
bx !
$end
#10
0D
0E
bx ?
bx J
bx U
b0 =
b0 K
b0 k
b0 9
b0 R
b0 l
0:
0'
02
0/
0,
0+
0*
0$
0.
06
0C
b10 n
b1 m
1%
0#
0"
#20
1>
b0 -
b0 u
b0 y
b10 n
b0 Z
b0 <
b0 M
b0 V
b0 w
b0 !
b0 5
b0 ?
b0 J
b0 U
b0 &
b0 }
b0 D"
b0 _
b0 I
b0 |
b0 {
b0 z
b0 4
b0 S
b0 p
b0 B
b0 H
b0 @
b0 L
b0 P
b0 ;
b0 F
b0 W
b0 x
b0 B"
b0 7
b0 T
b0 [
b0 ^
b0 8
b0 N
b0 Y
b0 1
b0 t
b0 C"
b0 3
b0 o
b0 r
b0 A
b0 G
b0 O
b0 v
1"
#30
0"
#40
b10100000000010010010000011 0
b10100000000010010010000011 \
b10100000000010010010000011 q
b10100000000010010010000011 s
b0 (
b0 ]
b0 !"
b0 )
b0 X
b0 ~
1"
#50
0"
0%
1#
#60
0>
1D
b100 -
b100 u
b100 y
b100 <
b100 M
b100 V
b100 w
b100 ?
b100 J
b100 U
b1 9
b1 R
b1 l
12
1*
1.
16
b100 n
b10100000000010010010000011 1
b10100000000010010010000011 t
b10100000000010010010000011 C"
b10 m
1"
#70
0"
#80
0D
b101100 -
b101100 u
b101100 y
b101100 <
b101100 M
b101100 V
b101100 w
b100 Z
b101000 ?
b101000 J
b101000 U
b100 @
b100 L
b100 P
b11 _
b11 I
b1001 |
b1000 {
b101000 4
b101000 S
b101000 p
b100 !
b100 5
b100 B
b100 H
b100 &
b100 }
b100 D"
b1000 n
b10 9
b10 R
b10 l
02
0*
0.
06
b100 A
b100 G
b100 O
b100 v
b10100000000010010010000011 3
b10100000000010010010000011 o
b10100000000010010010000011 r
b100 ;
b100 F
b100 W
b100 x
b100 B"
b100 m
1"
#90
0"
#100
b101000 -
b101000 u
b101000 y
b101000 <
b101000 M
b101000 V
b101000 w
b0 @
b0 L
b0 P
b101100 !
b101100 5
b101100 &
b101100 }
b101100 D"
1:
b10000 n
b10 9
b10 R
b10 l
b101100 ;
b101100 F
b101100 W
b101100 x
b101100 B"
bx 7
bx T
bx [
bx ^
b10110000000010010100000011 0
b10110000000010010100000011 \
b10110000000010010100000011 q
b10110000000010010100000011 s
b1000 m
bx (
bx ]
bx !"
1"
#110
0"
#120
b101000 Z
b101000 !
b101000 5
b101000 B
b101000 H
b101000 &
b101000 }
b101000 D"
1C
1.
16
b100000 n
b10 9
b10 R
b10 l
1:
b10110000000010010100000011 1
b10110000000010010100000011 t
b10110000000010010100000011 C"
b101000 ;
b101000 F
b101000 W
b101000 x
b101000 B"
b10000 m
1"
#130
0"
#140
bx -
bx u
bx y
bx <
bx M
bx V
bx w
b100 Z
b10110000000010010100000011 &
b10110000000010010100000011 }
b10110000000010010100000011 D"
bx ?
bx J
bx U
b100 @
b100 L
b100 P
b100 B
b100 H
1'
1/
b1000000 n
b0 9
b0 R
b0 l
0:
0.
06
0C
b110 0
b110 \
b110 q
b110 s
b100000 m
1"
#150
0"
#160
bx !
bx 5
b110 &
b110 }
b110 D"
b10 n
1'
1/
b10110000000010010100000011 0
b10110000000010010100000011 \
b10110000000010010100000011 q
b10110000000010010100000011 s
b110 1
b110 t
b110 C"
bx ;
bx F
bx W
bx x
bx B"
b1000000 m
1"
#170
0"
#180
1D
b1000 -
b1000 u
b1000 y
b1000 <
b1000 M
b1000 V
b1000 w
b100 ?
b100 J
b100 U
bx &
bx }
bx D"
b1 9
b1 R
b1 l
12
1*
1.
16
b100 n
0'
0/
b10110000000010010100000011 1
b10110000000010010100000011 t
b10110000000010010100000011 C"
b10 m
1"
#190
0"
#200
0D
b110100 -
b110100 u
b110100 y
b110100 <
b110100 M
b110100 V
b110100 w
b1000 Z
b101100 ?
b101100 J
b101100 U
b1000 @
b1000 L
b1000 P
b1010 |
b1100 {
b101100 4
b101100 S
b101100 p
b1000 !
b1000 5
b1000 B
b1000 H
b1000 &
b1000 }
b1000 D"
b1000 n
b10 9
b10 R
b10 l
02
0*
0.
06
b1000 A
b1000 G
b1000 O
b1000 v
b10110000000010010100000011 3
b10110000000010010100000011 o
b10110000000010010100000011 r
b1000 ;
b1000 F
b1000 W
b1000 x
b1000 B"
b100 m
1"
#210
0"
#220
b101100 -
b101100 u
b101100 y
b101100 <
b101100 M
b101100 V
b101100 w
b0 @
b0 L
b0 P
b110100 !
b110100 5
b110100 &
b110100 }
b110100 D"
1:
b10000 n
b10 9
b10 R
b10 l
b110100 ;
b110100 F
b110100 W
b110100 x
b110100 B"
b101001001000010110110011 0
b101001001000010110110011 \
b101001001000010110110011 q
b101001001000010110110011 s
b1000 m
1"
#230
0"
#240
b101100 Z
b101100 !
b101100 5
b101100 B
b101100 H
b101100 &
b101100 }
b101100 D"
1C
1.
16
b100000 n
b10 9
b10 R
b10 l
1:
b101001001000010110110011 1
b101001001000010110110011 t
b101001001000010110110011 C"
b101100 ;
b101100 F
b101100 W
b101100 x
b101100 B"
b10000 m
1"
#250
0"
