control.v
/* 
Module => control
Purpose => main controller of the design
        Generates various control signals needed in the design
*/


module control(  input clk, input rst, input [6:0] instOpcode, 
                output reg IorDSelector, output reg ce, output reg oce, output reg wre, output reg pcWriteEnable, output reg memtoRegSelect, output reg irWriteEnable, 
                        output reg regWriteEnable, output reg aluSrcASelect, output reg [1:0] aluSrcBSelect, output reg [1:0] aluOp );
    
    // 10 States - one hot encoding
    reg [10:0] currentState;
    reg [10:0] nextState;
    // state definition
    localparam
        idle =                  11'b00000000001,
        instFetch =             11'b00000000010,
        instDecodeRegFetch =    11'b00000000100,
        memoryAddrCompute =     11'b00000001000,
        memoryReadAccess =      11'b00000010000,
        memoryReadComplete =    11'b00000100000,
        mdrToRegFile =          11'b00001000000,
        memoryWriteAccess =     11'b00010000000,
        rTypeExecute =          11'b00100000000,
        rTypeComplete =         11'b01000000000,
        branchComplete =        11'b10000000000;
    
    // Sequential logic for state transition
    // asynchronous rst
    always@(posedge clk or posedge rst) begin
        if(rst) begin
            // reset to initial state
            currentState <= idle;
        end else begin
            // state transition
            currentState <= nextState;
        end
    end

    always@(*) begin
        //Default assignments
        nextState = currentState;
        IorDSelector = 1'b0;
        // memory controls
        ce = 1'b0;  // clock enable input for memory, active high
        oce = 1'b0; // output clock enable for memory, signal used in pipeline, invalid in Bypass
        wre = 1'b0; // write enable input, 1: write, 0: read
        pcWriteEnable = 1'b0;
        memtoRegSelect = 1'b0;
        irWriteEnable = 1'b0;
        regWriteEnable = 1'b0;
        aluSrcASelect = 1'b0;
        aluSrcBSelect = 2'b00;
        aluOp = 2'b00;

        // state machine logic
        case(currentState)
            // idle state hex is 1
            idle: begin
                nextState = instFetch;
            end
            // instFetch state hex is 2
            instFetch: begin
                nextState = instDecodeRegFetch;
                // enables and selectors
                IorDSelector = 1'b0;
                ce = 1'b1;
                oce = 1'b1;
                wre = 1'b0;
                pcWriteEnable = 1'b1;
                memtoRegSelect = 1'b0;
                irWriteEnable = 1'b1;
                regWriteEnable = 1'b0;
                aluSrcASelect = 1'b0;
                aluSrcBSelect = 2'b01;
                aluOp = 2'b00;
            end
            // instDecodeRegFetch state hex is 4
            instDecodeRegFetch: begin
                if(instOpcode == 7'h03) begin
                    nextState = memoryAddrCompute;
                end else begin
                    nextState = rTypeExecute;
                end
                ce = 1'b0;
                oce = 1'b0;
                // changing ALU input to immediate generator output to calculate branch address
                aluSrcASelect = 1'b0;
                aluSrcBSelect = 2'b10;
                aluOp = 2'b00;
            end
            // memoryAddrCompute state hex is 8
            memoryAddrCompute: begin
                if(instOpcode == 7'h03) begin
                    nextState = memoryReadAccess;
                end else begin
                    nextState = memoryWriteAccess;
                end
                aluSrcASelect = 1'b1;
                aluSrcBSelect = 2'b10;
                aluOp = 2'b00;
            end
            // memoryReadAccess state hex is 10
            memoryReadAccess: begin
                nextState = memoryReadComplete;
                ce = 1'b1;
                oce = 1'b1;
                IorDSelector = 1'b1;
                aluSrcASelect = 1'b1;
                aluSrcBSelect = 2'b10;
                aluOp = 2'b00;
            end
            // memoryReadComplete state hex is 20
            memoryReadComplete: begin
                nextState = mdrToRegFile;
                ce = 1'b0;
                oce = 1'b0;
                IorDSelector = 1'b0;
                memtoRegSelect = 1'b1;
                regWriteEnable = 1'b1;
            end
            // mdrToRegFile state hex is 40
            mdrToRegFile: begin
                nextState = instFetch;
                ce = 1'b0;
                oce = 1'b0;
                IorDSelector = 1'b0;
                memtoRegSelect = 1'b1;
                regWriteEnable = 1'b1;
            end
            // memoryWriteAccess state hex is 80
            memoryWriteAccess: begin
                nextState = instFetch;
                ce = 1'b1;
                oce = 1'b1;
                wre = 1'b1;
                IorDSelector = 1'b1;
            end
            // rTypeExecute state hex is 100
            rTypeExecute: begin
                nextState = rTypeComplete;
                aluSrcASelect = 1'b1;
                aluSrcBSelect = 2'b00;
                // aluOp= 2'10 indicates that the operation will be decided by opcode of instruction
                aluOp = 2'b10;
            end
            // rTypeComplete state hex is 200
            rTypeComplete: begin
                nextState = instFetch;
                regWriteEnable = 1'b1;
                memtoRegSelect = 1'b0;
            end
            // branchComplete state hex is 400
            branchComplete: begin
                nextState = instFetch;

            end
            default: begin
                nextState = idle;
                IorDSelector = 1'b0;
                ce = 1'b0;  
                oce = 1'b0; 
                wre = 1'b0; 
                pcWriteEnable = 1'b0;
                memtoRegSelect = 1'b0;
                irWriteEnable = 1'b0;
                regWriteEnable = 1'b0;
                aluSrcASelect = 1'b0;
                aluSrcBSelect = 2'b00;
                aluOp = 2'b00;
            end
        endcase
    end



endmodule

top.v
/* 
Module => top
Purpose => top module of the design 
Input description =>
    1. clk => central ticker of the system, on each positive edge of the clock things happen
    2. rst => reset signal of the system
Output description =>
    1. fDataOut => 6 bit output data to visualize on 6 LEDs of tang nano 9k
*/

`include "alu.v"
`include "rf.v"
`include "immGen.v"
`include "control.v"
`include "basicMemory.v"
//`include "gowin_sp/gowin_sp.v"

module mux2 (input [31:0] in0, in1, input select, output reg [31:0] out);
    always @(*) begin
        case(select)
            1'b0: out = in0;
            1'b1: out = in1;
        endcase
    end
endmodule

module mux3 (input [31:0] in0, in1, in2, input [1:0] select, output reg [31:0] out);
    always @(*) begin
        case(select)
            2'b00: out = in0;
            2'b01: out = in1;
            2'b10: out = in2;
            default: out = in1;
        endcase
    end
endmodule

module regWithEnable (input clk, input rst ,input enable, input [31:0] regIn, output reg [31:0] regOut);
    always@(posedge clk) begin
        if(rst == 1'b1) begin
            regOut <= 32'h0000;
        end
        else begin
            if(enable == 1'b1) begin
                regOut <= regIn;
            end
        end
    end
endmodule

module regWithoutEnable (input clk, input rst, input [31:0] regIn, output reg [31:0] regOut);
    always@(posedge clk) begin
        if(rst == 1'b1) begin
            regOut <= 32'h0000;
        end
        else begin
            regOut <= regIn;
        end
    end
endmodule

module top( input clk, nrst, output [5:0] fDataOut);

    // on tang nano, buttons are pulled high so whenever the button is pressed, we get low so our rst will be active low. hence the name nrst.
    // converting acrive low reset of tang nano to active high
    wire rst = !nrst;

    wire [31:0] addrInPcNet, addrOutPcNet;
    wire [31:0] aluOutNet;
    wire [31:0] memoryDataOutNet;
    wire [31:0] irOutNet;
    wire [31:0] mdrOutNet;
    wire [31:0] rfWriteDataMuxOutNet;
    wire [31:0] readData1Net;
    wire [31:0] readData2Net;
    wire [31:0] arOutNet;
    wire [31:0] brOutNet;
    wire [31:0] aluAmuxOutNet;
    wire [31:0] aluBmuxOutNet;
    wire [31:0] immGenOutNet;
    wire [31:0] IorDmuxOutNet;
    wire IorDSelectorNet, ceNet, oceNet, wreNet, pcWriteEnableNet, memtoRegSelectNet, irWriteEnableNet, regWriteEnableNet, aluSrcASelectNet;
    wire [1:0] aluSrcBSelectNet;
    wire [1:0] aluOpNet;

   
    // instantiating all the modules
    regWithEnable u_pc(.clk(clk), .rst(rst), .enable(pcWriteEnableNet), .regIn(addrInPcNet), .regOut(addrOutPcNet));
    mux2 u_IorDmux(.in0(addrOutPcNet), .in1(aluOutNet), .select(IorDSelectorNet), .out(IorDmuxOutNet));
    //Gowin_SP u_spmem(.dout(memoryDataOutNet), .clk(clk), .oce(oceNet), .ce(ceNet), .reset(rst), .wre(wreNet), .ad(IorDmuxOutNet[7:0]), .din(brOutNet));
    basicMemory u_basicMemory(.clk(clk), .rst(rst), .ce(ceNet), .wre(wreNet), .ad(IorDmuxOutNet[7:0]), .din(brOutNet), .dout(memoryDataOutNet));
    regWithEnable u_ir(.clk(clk), .rst(rst), .enable(irWriteEnableNet), .regIn(memoryDataOutNet), .regOut(irOutNet));
    regWithoutEnable u_mdr(.clk(clk), .rst(rst), .regIn(memoryDataOutNet), .regOut(mdrOutNet));
    mux2 u_rfWriteDataMux(.in0(aluOutNet), .in1(mdrOutNet), .select(memtoRegSelectNet), .out(rfWriteDataMuxOutNet));
    rf u_rf(.clk(clk), .regWriteEnable(regWriteEnableNet), .readReg1(irOutNet[19:15]), .readReg2(irOutNet[24:20]), .writeReg(irOutNet[11:7]), .readData1(readData1Net), .readData2(readData2Net),.writeData(rfWriteDataMuxOutNet));
    regWithoutEnable u_ar(.clk(clk), .rst(rst), .regIn(readData1Net), .regOut(arOutNet));
    mux2 u_aluAmux(.in0(addrOutPcNet), .in1(arOutNet), .select(aluSrcASelectNet), .out(aluAmuxOutNet));
    regWithoutEnable u_br(.clk(clk), .rst(rst), .regIn(readData2Net), .regOut(brOutNet));
    mux3 u_aluBmux(.in0(brOutNet),.in1(32'h00000004),.in2(immGenOutNet),.select(aluSrcBSelectNet),.out(aluBmuxOutNet));
    immGen u_immGen(.instr(irOutNet),.imm(immGenOutNet));
    alu u_alu(.ALUop(aluOpNet), .instOpcode(irOutNet[6:0]), .A(aluAmuxOutNet), .B(aluBmuxOutNet), .Z(addrInPcNet));
    regWithoutEnable u_alur(.clk(clk),  .rst(rst), .regIn(addrInPcNet), .regOut(aluOutNet));
    control u_control(.clk(clk), .rst(rst), .instOpcode(irOutNet[6:0]), .IorDSelector(IorDSelectorNet), .ce(ceNet), .oce(oceNet), .wre(wreNet), .pcWriteEnable(pcWriteEnableNet), .memtoRegSelect(memtoRegSelectNet),
                .irWriteEnable(irWriteEnableNet), .regWriteEnable(regWriteEnableNet), .aluSrcASelect(aluSrcASelectNet), .aluSrcBSelect(aluSrcBSelectNet), .aluOp(aluOpNet));

    assign fDataOut = aluOutNet[5:0];
endmodule

/*
Commands to generate waveform-
iverilog -o top_tb.vvp top_tb.v
vvp top_tb.vvp
gtkwave top_tb.vcd signals.gtkw
*/

alu.v
/* 
Module => alu
Purpose => Arithmetic Logic Unit i.e. the computation unit of the CPU
Input description =>
    1. 
    2. 
Output description =>
    1. 
*/
module alu(input [1:0] ALUop, input [6:0] instOpcode,input [31:0] A , input [31:0] B, output reg [31:0] Z);

always@(*) begin
    case(ALUop)
        2'b00: Z = A + B ;
        2'b01: Z = A - B ;
        // following two are fake, need to update
        2'b10: begin
            if (instOpcode == 7'h33) begin
                // 7'h33 is opcode for add
                // TODO -- need to add funct3 and funct7 bits also as sub has same opcode but different funct bits
                Z = A + B; 
            end else begin
                Z = A - B;
            end
        end
        2'b11: Z = A + B ;
    endcase
end
endmodule

immGen.v
/* 
Module => immGen
Purpose => Immediate generation unit, it has to generate 32bit immediates from all types of instructions. 
Input description =>
    1. instr - 32 bit instruction
Output description =>
    1. imm - 32 bit immediate
*/
module immGen( input [31:0] instr, output reg [31:0] imm);
always@(*) begin
    if (instr[6:0] == 7'h03 && instr[14:12] == 3'b010) begin
        // immediate generation for 'lw'
        imm = {20'h00000,instr[31:20]};
    end else if (instr[6:0] == 7'h63 && instr[14:12] == 3'b000) begin
        // immediate generation for 'beq'
        if (instr[31] == 1'b1) begin
            imm = {20'hFFFFF,instr[31],instr[7],instr[30:25],instr[11:8],1'b0};
        end else begin
            imm = {20'h00000,instr[31],instr[7],instr[30:25],instr[11:8],1'b0};
        end
    end 
    else begin
        imm = 32'h0;
    end
end
endmodule

rf.v
/* 
Module => rf
Purpose => register file, it containts all the 32 registers of RISC-V CPU
Input description =>
    1. clk => central ticker of the system, on each positive edge of the clock, it loads the input value
    2. regWriteEnable => active high signal to enable writing to the register file
    3. readReg1 and readReg2 => 5 bit address of the registers whose data needs to be presented on readData1 and readData2 respectively
    4. writeReg => 5 bit address of regiser to be written
    5. writeData => data to write in register selected by writeReg
Output description =>
    1. readData1 and readData2 => output data from registers specified by readReg1 and readReg2 respectively
*/
module rf(input clk, input regWriteEnable,
                     input [4:0] readReg1,
                     input [4:0] readReg2, 
                     input [4:0] writeReg, input [31:0] writeData, 
                    output reg [31:0] readData1, output reg [31:0] readData2);

    // 32 registers each 32 bit wide
    reg [31:0] registersOfRegFile [31:0];
    // setting 0 register to always be 0
    initial begin
        registersOfRegFile[0] <= 32'b0; 
    end


    // write logic
    genvar i;
    generate 
        for (i=0; i<32; i=i+1) begin: reg_write
            always@(posedge clk) begin
                if (regWriteEnable == 1'b1 && (writeReg == i) && (writeReg != 5'b0)) begin
                    registersOfRegFile[i] <= writeData ;
                end 
            end
        end
    endgenerate


    //read logic
    always @(posedge clk) begin
        readData1 = registersOfRegFile[readReg1];
        readData2 = registersOfRegFile[readReg2];
    end
endmodule

basicMemory.v
/* creating basic memory to help simulation in vscode, as gowin IP won't work. */

module basicMemory(input clk, input rst, input ce, input wre, input [7:0] ad, input [31:0] din, output reg [31:0] dout);

    reg [31:0] memStoreArray [255:0];

    initial begin
        memStoreArray[0] = 32'h02802483;  // lw x9, 40(x0)
        memStoreArray[4] = 32'h02C02503;  // lw x10, 44(x0)
        memStoreArray[8] = 32'h00A485B3;  // add x11, x9, x10
        memStoreArray[12] = 32'hFE000EE3; // beq x0, x0, -4 ; instruction format is B type so needs special treatment for immediate generation
        memStoreArray[40] = 32'h00000006;
        memStoreArray[44] = 32'h00000005;
    end

    always@(posedge clk) begin
        if(wre) begin
            memStoreArray[ad] <= din;
        end else begin
           dout <= memStoreArray[ad]; 
        end
    end

endmodule

top_tb.v
`timescale 1ns / 1ns
`include "top.v"

module top_tb;

reg clk = 0;
reg nrst;
wire [5:0] fDataOut;

top u_top(.clk(clk), .nrst(nrst),.fDataOut(fDataOut));

always begin
    clk = ~clk;
    #10;
end

initial begin
    $dumpfile("top_tb.vcd");
    $dumpvars(0, top_tb);

    #10
    nrst = 1'b0;
    #40
    nrst = 1'b1;

    #1000

    #10
    nrst = 1'b0;
    #40
    nrst = 1'b1;

    #1000

    $finish;
end

endmodule

top_tb.vcd
$date
	Mon Dec 23 21:49:34 2024
$end
$version
	Icarus Verilog
$end
$timescale
	1ns
$end
$scope module top_tb $end
$var wire 6 ! fDataOut [5:0] $end
$var reg 1 " clk $end
$var reg 1 # nrst $end
$scope module u_top $end
$var wire 1 " clk $end
$var wire 1 # nrst $end
$var wire 1 $ wreNet $end
$var wire 1 % rst $end
$var wire 32 & rfWriteDataMuxOutNet [31:0] $end
$var wire 1 ' regWriteEnableNet $end
$var wire 32 ( readData2Net [31:0] $end
$var wire 32 ) readData1Net [31:0] $end
$var wire 1 * pcWriteEnableNet $end
$var wire 1 + oceNet $end
$var wire 1 , memtoRegSelectNet $end
$var wire 32 - memoryDataOutNet [31:0] $end
$var wire 32 . mdrOutNet [31:0] $end
$var wire 1 / irWriteEnableNet $end
$var wire 32 0 irOutNet [31:0] $end
$var wire 32 1 immGenOutNet [31:0] $end
$var wire 6 2 fDataOut [5:0] $end
$var wire 1 3 ceNet $end
$var wire 32 4 brOutNet [31:0] $end
$var wire 32 5 arOutNet [31:0] $end
$var wire 2 6 aluSrcBSelectNet [1:0] $end
$var wire 1 7 aluSrcASelectNet $end
$var wire 32 8 aluOutNet [31:0] $end
$var wire 2 9 aluOpNet [1:0] $end
$var wire 32 : aluBmuxOutNet [31:0] $end
$var wire 32 ; aluAmuxOutNet [31:0] $end
$var wire 32 < addrOutPcNet [31:0] $end
$var wire 32 = addrInPcNet [31:0] $end
$var wire 32 > IorDmuxOutNet [31:0] $end
$var wire 1 ? IorDSelectorNet $end
$scope module u_IorDmux $end
$var wire 1 ? select $end
$var wire 32 @ in1 [31:0] $end
$var wire 32 A in0 [31:0] $end
$var reg 32 B out [31:0] $end
$upscope $end
$scope module u_alu $end
$var wire 7 C instOpcode [6:0] $end
$var wire 32 D B [31:0] $end
$var wire 2 E ALUop [1:0] $end
$var wire 32 F A [31:0] $end
$var reg 32 G Z [31:0] $end
$upscope $end
$scope module u_aluAmux $end
$var wire 1 7 select $end
$var wire 32 H in1 [31:0] $end
$var wire 32 I in0 [31:0] $end
$var reg 32 J out [31:0] $end
$upscope $end
$scope module u_aluBmux $end
$var wire 32 K in1 [31:0] $end
$var wire 2 L select [1:0] $end
$var wire 32 M in2 [31:0] $end
$var wire 32 N in0 [31:0] $end
$var reg 32 O out [31:0] $end
$upscope $end
$scope module u_alur $end
$var wire 1 " clk $end
$var wire 32 P regIn [31:0] $end
$var wire 1 % rst $end
$var reg 32 Q regOut [31:0] $end
$upscope $end
$scope module u_ar $end
$var wire 1 " clk $end
$var wire 1 % rst $end
$var wire 32 R regIn [31:0] $end
$var reg 32 S regOut [31:0] $end
$upscope $end
$scope module u_basicMemory $end
$var wire 8 T ad [7:0] $end
$var wire 1 " clk $end
$var wire 1 % rst $end
$var wire 1 $ wre $end
$var wire 32 U din [31:0] $end
$var wire 1 3 ce $end
$var reg 32 V dout [31:0] $end
$upscope $end
$scope module u_br $end
$var wire 1 " clk $end
$var wire 1 % rst $end
$var wire 32 W regIn [31:0] $end
$var reg 32 X regOut [31:0] $end
$upscope $end
$scope module u_control $end
$var wire 1 " clk $end
$var wire 7 Y instOpcode [6:0] $end
$var wire 1 % rst $end
$var parameter 11 Z branchComplete $end
$var parameter 11 [ idle $end
$var parameter 11 \ instDecodeRegFetch $end
$var parameter 11 ] instFetch $end
$var parameter 11 ^ mdrToRegFile $end
$var parameter 11 _ memoryAddrCompute $end
$var parameter 11 ` memoryReadAccess $end
$var parameter 11 a memoryReadComplete $end
$var parameter 11 b memoryWriteAccess $end
$var parameter 11 c rTypeComplete $end
$var parameter 11 d rTypeExecute $end
$var reg 1 ? IorDSelector $end
$var reg 2 e aluOp [1:0] $end
$var reg 1 7 aluSrcASelect $end
$var reg 2 f aluSrcBSelect [1:0] $end
$var reg 1 3 ce $end
$var reg 11 g currentState [10:0] $end
$var reg 1 / irWriteEnable $end
$var reg 1 , memtoRegSelect $end
$var reg 11 h nextState [10:0] $end
$var reg 1 + oce $end
$var reg 1 * pcWriteEnable $end
$var reg 1 ' regWriteEnable $end
$var reg 1 $ wre $end
$upscope $end
$scope module u_immGen $end
$var wire 32 i instr [31:0] $end
$var reg 32 j imm [31:0] $end
$upscope $end
$scope module u_ir $end
$var wire 1 " clk $end
$var wire 1 / enable $end
$var wire 32 k regIn [31:0] $end
$var wire 1 % rst $end
$var reg 32 l regOut [31:0] $end
$upscope $end
$scope module u_mdr $end
$var wire 1 " clk $end
$var wire 32 m regIn [31:0] $end
$var wire 1 % rst $end
$var reg 32 n regOut [31:0] $end
$upscope $end
$scope module u_pc $end
$var wire 1 " clk $end
$var wire 1 * enable $end
$var wire 32 o regIn [31:0] $end
$var wire 1 % rst $end
$var reg 32 p regOut [31:0] $end
$upscope $end
$scope module u_rf $end
$var wire 1 " clk $end
$var wire 5 q readReg1 [4:0] $end
$var wire 5 r readReg2 [4:0] $end
$var wire 1 ' regWriteEnable $end
$var wire 5 s writeReg [4:0] $end
$var wire 32 t writeData [31:0] $end
$var reg 32 u readData1 [31:0] $end
$var reg 32 v readData2 [31:0] $end
$scope begin reg_write[0] $end
$var parameter 2 w i $end
$upscope $end
$scope begin reg_write[1] $end
$var parameter 2 x i $end
$upscope $end
$scope begin reg_write[2] $end
$var parameter 3 y i $end
$upscope $end
$scope begin reg_write[3] $end
$var parameter 3 z i $end
$upscope $end
$scope begin reg_write[4] $end
$var parameter 4 { i $end
$upscope $end
$scope begin reg_write[5] $end
$var parameter 4 | i $end
$upscope $end
$scope begin reg_write[6] $end
$var parameter 4 } i $end
$upscope $end
$scope begin reg_write[7] $end
$var parameter 4 ~ i $end
$upscope $end
$scope begin reg_write[8] $end
$var parameter 5 !" i $end
$upscope $end
$scope begin reg_write[9] $end
$var parameter 5 "" i $end
$upscope $end
$scope begin reg_write[10] $end
$var parameter 5 #" i $end
$upscope $end
$scope begin reg_write[11] $end
$var parameter 5 $" i $end
$upscope $end
$scope begin reg_write[12] $end
$var parameter 5 %" i $end
$upscope $end
$scope begin reg_write[13] $end
$var parameter 5 &" i $end
$upscope $end
$scope begin reg_write[14] $end
$var parameter 5 '" i $end
$upscope $end
$scope begin reg_write[15] $end
$var parameter 5 (" i $end
$upscope $end
$scope begin reg_write[16] $end
$var parameter 6 )" i $end
$upscope $end
$scope begin reg_write[17] $end
$var parameter 6 *" i $end
$upscope $end
$scope begin reg_write[18] $end
$var parameter 6 +" i $end
$upscope $end
$scope begin reg_write[19] $end
$var parameter 6 ," i $end
$upscope $end
$scope begin reg_write[20] $end
$var parameter 6 -" i $end
$upscope $end
$scope begin reg_write[21] $end
$var parameter 6 ." i $end
$upscope $end
$scope begin reg_write[22] $end
$var parameter 6 /" i $end
$upscope $end
$scope begin reg_write[23] $end
$var parameter 6 0" i $end
$upscope $end
$scope begin reg_write[24] $end
$var parameter 6 1" i $end
$upscope $end
$scope begin reg_write[25] $end
$var parameter 6 2" i $end
$upscope $end
$scope begin reg_write[26] $end
$var parameter 6 3" i $end
$upscope $end
$scope begin reg_write[27] $end
$var parameter 6 4" i $end
$upscope $end
$scope begin reg_write[28] $end
$var parameter 6 5" i $end
$upscope $end
$scope begin reg_write[29] $end
$var parameter 6 6" i $end
$upscope $end
$scope begin reg_write[30] $end
$var parameter 6 7" i $end
$upscope $end
$scope begin reg_write[31] $end
$var parameter 6 8" i $end
$upscope $end
$upscope $end
$scope module u_rfWriteDataMux $end
$var wire 32 9" in0 [31:0] $end
$var wire 32 :" in1 [31:0] $end
$var wire 1 , select $end
$var reg 32 ;" out [31:0] $end
$upscope $end
$upscope $end
$upscope $end
$enddefinitions $end
$comment Show the parameter values. $end
$dumpall
b11111 8"
b11110 7"
b11101 6"
b11100 5"
b11011 4"
b11010 3"
b11001 2"
b11000 1"
b10111 0"
b10110 /"
b10101 ."
b10100 -"
b10011 ,"
b10010 +"
b10001 *"
b10000 )"
b1111 ("
b1110 '"
b1101 &"
b1100 %"
b1011 $"
b1010 #"
b1001 ""
b1000 !"
b111 ~
b110 }
b101 |
b100 {
b11 z
b10 y
b1 x
b0 w
b100000000 d
b1000000000 c
b10000000 b
b100000 a
b10000 `
b1000 _
b1000000 ^
b10 ]
b100 \
b1 [
b10000000000 Z
$end
#0
$dumpvars
bx ;"
bx :"
bx 9"
bx v
bx u
bx t
bx s
bx r
bx q
bx p
bx o
bx n
bx m
bx l
bx k
bx j
bx i
bx h
bx g
bx f
bx e
bx Y
bx X
bx W
bx V
bx U
bx T
bx S
bx R
bx Q
bx P
b100 O
bx N
bx M
bx L
b100 K
bx J
bx I
bx H
bx G
bx F
bx E
b100 D
bx C
bx B
bx A
bx @
x?
bx >
bx =
bx <
bx ;
b100 :
bx 9
bx 8
x7
bx 6
bx 5
bx 4
x3
bx 2
bx 1
bx 0
x/
bx .
bx -
x,
x+
x*
bx )
bx (
x'
bx &
x%
x$
x#
1"
bx !
$end
#10
bx :
bx D
bx O
b0 9
b0 E
b0 e
b0 6
b0 L
b0 f
07
0'
0/
0,
0*
0$
0+
03
0?
b10 h
b1 g
1%
0#
0"
#20
b10 h
b0 T
b0 =
b0 G
b0 P
b0 o
b0 !
b0 2
b0 :
b0 D
b0 O
b0 &
b0 t
b0 ;"
b0 Y
b0 C
b0 s
b0 r
b0 q
b0 1
b0 M
b0 j
b0 >
b0 B
b0 ;
b0 F
b0 J
b0 8
b0 @
b0 Q
b0 9"
b0 4
b0 N
b0 U
b0 X
b0 5
b0 H
b0 S
b0 .
b0 n
b0 :"
b0 0
b0 i
b0 l
b0 <
b0 A
b0 I
b0 p
1"
#30
0"
#40
b10100000000010010010000011 -
b10100000000010010010000011 V
b10100000000010010010000011 k
b10100000000010010010000011 m
b0 (
b0 W
b0 v
b0 )
b0 R
b0 u
1"
#50
0"
0%
1#
#60
b100 =
b100 G
b100 P
b100 o
b100 :
b100 D
b100 O
b1 6
b1 L
b1 f
1/
1*
1+
13
b100 h
b10100000000010010010000011 .
b10100000000010010010000011 n
b10100000000010010010000011 :"
b10 g
1"
#70
0"
#80
b101100 =
b101100 G
b101100 P
b101100 o
b100 T
b101000 :
b101000 D
b101000 O
b100 ;
b100 F
b100 J
b11 Y
b11 C
b1001 s
b1000 r
b101000 1
b101000 M
b101000 j
b100 !
b100 2
b100 >
b100 B
b100 &
b100 t
b100 ;"
b1000 h
b10 6
b10 L
b10 f
0/
0*
0+
03
b100 <
b100 A
b100 I
b100 p
b10100000000010010010000011 0
b10100000000010010010000011 i
b10100000000010010010000011 l
b100 8
b100 @
b100 Q
b100 9"
b100 g
1"
#90
0"
#100
b101000 =
b101000 G
b101000 P
b101000 o
b0 ;
b0 F
b0 J
b101100 !
b101100 2
b101100 &
b101100 t
b101100 ;"
17
b10000 h
b10 6
b10 L
b10 f
b101100 8
b101100 @
b101100 Q
b101100 9"
bx 4
bx N
bx U
bx X
b10110000000010010100000011 -
b10110000000010010100000011 V
b10110000000010010100000011 k
b10110000000010010100000011 m
b1000 g
bx (
bx W
bx v
1"
#110
0"
#120
b101000 T
b101000 !
b101000 2
b101000 >
b101000 B
b101000 &
b101000 t
b101000 ;"
1?
1+
13
b100000 h
b10 6
b10 L
b10 f
17
b10110000000010010100000011 .
b10110000000010010100000011 n
b10110000000010010100000011 :"
b101000 8
b101000 @
b101000 Q
b101000 9"
b10000 g
1"
#130
0"
#140
bx =
bx G
bx P
bx o
b100 T
b10110000000010010100000011 &
b10110000000010010100000011 t
b10110000000010010100000011 ;"
bx :
bx D
bx O
b100 ;
b100 F
b100 J
b100 >
b100 B
1'
1,
b1000000 h
b0 6
b0 L
b0 f
07
0+
03
0?
b110 -
b110 V
b110 k
b110 m
b100000 g
1"
#150
0"
#160
bx !
bx 2
b110 &
b110 t
b110 ;"
b10 h
1'
1,
b10110000000010010100000011 -
b10110000000010010100000011 V
b10110000000010010100000011 k
b10110000000010010100000011 m
b110 .
b110 n
b110 :"
bx 8
bx @
bx Q
bx 9"
b1000000 g
1"
#170
0"
#180
b1000 =
b1000 G
b1000 P
b1000 o
b100 :
b100 D
b100 O
bx &
bx t
bx ;"
b1 6
b1 L
b1 f
1/
1*
1+
13
b100 h
0'
0,
b10110000000010010100000011 .
b10110000000010010100000011 n
b10110000000010010100000011 :"
b10 g
1"
#190
0"
#200
b110100 =
b110100 G
b110100 P
b110100 o
b1000 T
b101100 :
b101100 D
b101100 O
b1000 ;
b1000 F
b1000 J
b1010 s
b1100 r
b101100 1
b101100 M
b101100 j
b1000 !
b1000 2
b1000 >
b1000 B
b1000 &
b1000 t
b1000 ;"
b1000 h
b10 6
b10 L
b10 f
0/
0*
0+
03
b1000 <
b1000 A
b1000 I
b1000 p
b10110000000010010100000011 0
b10110000000010010100000011 i
b10110000000010010100000011 l
b1000 8
b1000 @
b1000 Q
b1000 9"
b100 g
1"
#210
0"
#220
b101100 =
b101100 G
b101100 P
b101100 o
b0 ;
b0 F
b0 J
b110100 !
b110100 2
b110100 &
b110100 t
b110100 ;"
17
b10000 h
b10 6
b10 L
b10 f
b110100 8
b110100 @
b110100 Q
b110100 9"
b101001001000010110110011 -
b101001001000010110110011 V
b101001001000010110110011 k
b101001001000010110110011 m
b1000 g
1"
#230
0"
#240
b101100 T
b101100 !
b101100 2
b101100 >
b101100 B
b101100 &
b101100 t
b101100 ;"
1?
1+
13
b100000 h
b10 6
b10 L
b10 f
17
b101001001000010110110011 .
b101001001000010110110011 n
b101001001000010110110011 :"
b101100 8
b101100 @
b101100 Q
b101100 9"
b10000 g
1"
#250
0"
#260
bx =
bx G
bx P
bx o
b1000 T
b101001001000010110110011 &
b101001001000010110110011 t
b101001001000010110110011 ;"
bx :
bx D
bx O
b1000 ;
b1000 F
b1000 J
b1000 >
b1000 B
1'
1,
b1000000 h
b0 6
b0 L
b0 f
07
0+
03
0?
b101 -
b101 V
b101 k
b101 m
b100000 g
1"
#270
0"
#280
bx !
bx 2
b101 &
b101 t
b101 ;"
b10 h
1'
1,
b101001001000010110110011 -
b101001001000010110110011 V
b101001001000010110110011 k
b101001001000010110110011 m
b101 .
b101 n
b101 :"
bx 8
bx @
bx Q
bx 9"
b1000000 g
1"
#290
0"
#300
b1100 =
b1100 G
b1100 P
b1100 o
b100 :
b100 D
b100 O
bx &
bx t
bx ;"
b1 6
b1 L
b1 f
1/
1*
1+
13
b100 h
0'
0,
b101001001000010110110011 .
b101001001000010110110011 n
b101001001000010110110011 :"
b10 g
1"
#310
0"
#320
b1100 T
b0 :
b0 D
b0 O
b1100 ;
b1100 F
b1100 J
b110011 Y
b110011 C
b1011 s
b1010 r
b1001 q
b0 1
b0 M
b0 j
b1100 !
b1100 2
b1100 >
b1100 B
b1100 &
b1100 t
b1100 ;"
b100000000 h
b10 6
b10 L
b10 f
0/
0*
0+
03
b1100 <
b1100 A
b1100 I
b1100 p
b101001001000010110110011 0
b101001001000010110110011 i
b101001001000010110110011 l
b1100 8
b1100 @
b1100 Q
b1100 9"
b100 g
1"
#330
0"
#340
b1011 =
b1011 G
b1011 P
b1011 o
b101 :
b101 D
b101 O
b110 ;
b110 F
b110 J
b10 9
b10 E
b10 e
17
b1000000000 h
b0 6
b0 L
b0 f
b101 4
b101 N
b101 U
b101 X
b110 5
b110 H
b110 S
bx -
bx V
bx k
bx m
b100000000 g
b101 (
b101 W
b101 v
b110 )
b110 R
b110 u
1"
#350
0"
#360
b10001 =
b10001 G
b10001 P
b10001 o
b1100 ;
b1100 F
b1100 J
b1011 !
b1011 2
b1011 &
b1011 t
b1011 ;"
1'
b10 h
b0 9
b0 E
b0 e
07
bx .
bx n
bx :"
b1011 8
b1011 @
b1011 Q
b1011 9"
b1000000000 g
1"
#370
0"
#380
b10000 =
b10000 G
b10000 P
b10000 o
b100 :
b100 D
b100 O
b10001 !
b10001 2
b10001 &
b10001 t
b10001 ;"
b1 6
b1 L
b1 f
1/
1*
1+
13
b100 h
0'
b10001 8
b10001 @
b10001 Q
b10001 9"
b10 g
1"
#390
0"
